LICENCE
README.md
setup.py
api_fluid_0738.egg-info/PKG-INFO
api_fluid_0738.egg-info/SOURCES.txt
api_fluid_0738.egg-info/dependency_links.txt
api_fluid_0738.egg-info/requires.txt
api_fluid_0738.egg-info/top_level.txt
fluid_0738/__init__.py
fluid_0738/fluid.py