Metadata-Version: 2.1
Name: api-fluid-0738
Version: 0.0.2
Summary: Biblioteca de requests da API do Fluid
Author: Alex Abatti
Author-email: abattialex1999@gmail.com
License: MIT License
Keywords: api fluid
License-File: LICENCE
